py_register_machine2/__init__.py
py_register_machine2/setup.py
py_register_machine2/app/__init__.py
py_register_machine2/app/cli/__init__.py
py_register_machine2/app/cli/__main__.py
py_register_machine2/app/web/__init__.py
py_register_machine2/app/web/front.py
py_register_machine2/app/web/model.py
py_register_machine2/commands/__init__.py
py_register_machine2/commands/basic_commands.py
py_register_machine2/commands/gym_bav_16.py
py_register_machine2/commands/stack_based.py
py_register_machine2/core/__init__.py
py_register_machine2/core/commands.py
py_register_machine2/core/device.py
py_register_machine2/core/interrupts.py
py_register_machine2/core/memory.py
py_register_machine2/core/parts.py
py_register_machine2/core/processor.py
py_register_machine2/core/register.py
py_register_machine2/engine_tools/__init__.py
py_register_machine2/engine_tools/conversions.py
py_register_machine2/engine_tools/operations.py
py_register_machine2/engine_tools/output/__init__.py
py_register_machine2/engine_tools/output/gpu_alike/__init__.py
py_register_machine2/engine_tools/output/gpu_alike/http.py
py_register_machine2/engine_tools/output/gpu_alike/rendering.py
py_register_machine2/machines/__init__.py
py_register_machine2/machines/gym_bav_16.py
py_register_machine2/machines/small.py
py_register_machine2/tools/__init__.py
py_register_machine2/tools/assembler/__init__.py
py_register_machine2/tools/assembler/assembler.py
py_register_machine2/tools/assembler/directives.py
py_register_machine2-0.1.4.dist-info/DESCRIPTION.rst
py_register_machine2-0.1.4.dist-info/METADATA
py_register_machine2-0.1.4.dist-info/RECORD
py_register_machine2-0.1.4.dist-info/WHEEL
py_register_machine2-0.1.4.dist-info/metadata.json
py_register_machine2-0.1.4.dist-info/top_level.txt
