Metadata-Version: 2.0
Name: py-register-machine2
Version: 0.1.4
Summary: A Register Machine Package
Home-page: https://github.com/daknuett/py_register_machine2
Author: Daniel Knüttel
Author-email: daknuett@gmail.com
License: GPL v3
Keywords: simulation virtualization processor registermachine
Platform: UNKNOWN
Classifier: Development Status :: 4 - Beta
Classifier: Intended Audience :: Developers
Classifier: Intended Audience :: Education
Classifier: Intended Audience :: Information Technology
Classifier: Intended Audience :: Science/Research
Classifier: Topic :: Education
Classifier: Topic :: Education :: Testing
Classifier: License :: OSI Approved :: GNU General Public License v3 (GPLv3)
Classifier: Programming Language :: Python :: 3
Classifier: Programming Language :: Python :: 3.3
Classifier: Programming Language :: Python :: 3.4
Classifier: Programming Language :: Python :: 3.5
Requires-Dist: cherrypy (>=3.0)
Requires-Dist: docopt (>=0.6.1)
